djangoshop_gestpay-0.1.0.dist-info/DESCRIPTION.rst
djangoshop_gestpay-0.1.0.dist-info/LICENSE.txt
djangoshop_gestpay-0.1.0.dist-info/METADATA
djangoshop_gestpay-0.1.0.dist-info/RECORD
djangoshop_gestpay-0.1.0.dist-info/WHEEL
djangoshop_gestpay-0.1.0.dist-info/metadata.json
djangoshop_gestpay-0.1.0.dist-info/top_level.txt
shop_gestpay/__init__.py
shop_gestpay/forms.py
shop_gestpay/modifiers.py
shop_gestpay/payment.py
shop_gestpay/settings.py
shop_gestpay/templates/shop_gestpay/error.html
shop_gestpay/templates/shop_gestpay/payment.html
