Metadata-Version: 2.0
Name: djangoshop-gestpay
Version: 0.1.0
Summary: GestPay Payment integration for djangoSHOP.
Home-page: https://github.com/dinoperovic/djangoshop-gestpay
Author: Dino Perovic
Author-email: dino.perovic@gmail.com
License: BSD
Platform: OS Independent
Classifier: Environment :: Web Environment
Classifier: Framework :: Django
Classifier: Intended Audience :: Developers
Classifier: License :: OSI Approved :: BSD License
Classifier: Operating System :: OS Independent
Classifier: Programming Language :: Python :: 2.7
Classifier: Programming Language :: Python :: 3.4
Classifier: Programming Language :: Python :: 3.5
Requires-Dist: django-shop (>=0.9.3)
Requires-Dist: gestpypay (>=1.0.0)
